langchain_mcp/__init__.py
langchain_mcp/py.typed
langchain_mcp/toolkit.py
langchain_mcp-0.1.0.dist-info/METADATA
langchain_mcp-0.1.0.dist-info/WHEEL
langchain_mcp-0.1.0.dist-info/licenses/LICENSE
langchain_mcp-0.1.0.dist-info/RECORD
