Metadata-Version: 2.4
Name: langchain-mcp
Version: 0.1.0
Summary: Model Context Protocol tool calling support for LangChain
Project-URL: Repository, https://github.com/rectalogic/langchain-mcp
Project-URL: Issues, https://github.com/rectalogic/langchain-mcp/issues
Project-URL: Related, https://modelcontextprotocol.io/
Author-email: Andrew Wason <rectalogic@rectalogic.com>
License-File: LICENSE
Classifier: License :: OSI Approved :: MIT License
Requires-Python: >=3.10
Requires-Dist: langchain-core~=0.3.21
Requires-Dist: mcp~=1.0.0
Requires-Dist: pydantic~=2.10.2
Requires-Dist: typing-extensions~=4.12.2
